<Properties StartupConfiguration="{5DACD273-41F6-1C87-82F0-70BCCA112BF5}|">
  <MonoDevelop.Ide.Workbench ActiveDocument="Assets/Scripts/Vi/AI_Base.cs">
    <Files>
      <File FileName="Assets/Scripts/Vi/GameEventManager.cs" Line="1" Column="1" />
      <File FileName="Assets/Scripts/Vi/GameEventObserver.cs" />
      <File FileName="Assets/Scripts/Vi/AI_Demon.cs" Line="30" Column="6" />
      <File FileName="Assets/Scripts/Vi/AI_Base.cs" Line="276" Column="18" />
      <File FileName="Assets/Scripts/Charbel/PlayerDying.cs" />
    </Files>
    <Pads>
      <Pad Id="ProjectPad">
        <State name="__root__">
          <Node name="ActiveBystanders" expanded="True">
            <Node name="Assets" expanded="True">
              <Node name="Editor" expanded="True">
                <Node name="CrossPlatformInput" expanded="True" />
              </Node>
              <Node name="Export Cutscene" expanded="True" />
              <Node name="FirstPersion AIO Pack" expanded="True">
                <Node name="FirstPersonAIO" expanded="True" />
              </Node>
              <Node name="Scripts" expanded="True">
                <Node name="Charbel" expanded="True" />
                <Node name="Jordan" expanded="True" />
                <Node name="Mercurius" expanded="True" />
                <Node name="Vi" expanded="True">
                  <Node name="MainMenu" expanded="True" />
                  <Node name="AI_Base.cs" selected="True" />
                </Node>
              </Node>
            </Node>
          </Node>
        </State>
      </Pad>
    </Pads>
  </MonoDevelop.Ide.Workbench>
  <MonoDevelop.Ide.DebuggingService.PinnedWatches />
  <MonoDevelop.Ide.Workspace ActiveConfiguration="Debug" />
  <MonoDevelop.Ide.ItemProperties.Assembly-CSharp PreferredExecutionTarget="bc769cc9-2bc1-44d6-ae52-ebb9459245f5" />
  <MonoDevelop.Ide.DebuggingService.Breakpoints>
    <BreakpointStore />
  </MonoDevelop.Ide.DebuggingService.Breakpoints>
  <MultiItemStartupConfigurations />
</Properties>